{"nodes": [{"id": "c_users_jvele_documents_tesis_brazorobotico_src_gui_simulation_interface_py", "label": "simulation_interface.py", "file_type": "code", "source_file": "C:\\Users\\jvele\\Documents\\_Tesis\\BrazoRobotico\\src\\gui\\simulation_interface.py", "source_location": "L1"}, {"id": "gui_simulation_interface_siminterface", "label": "SimInterface", "file_type": "code", "source_file": "C:\\Users\\jvele\\Documents\\_Tesis\\BrazoRobotico\\src\\gui\\simulation_interface.py", "source_location": "L13"}, {"id": "imageutilsmixin", "label": "ImageUtilsMixin", "file_type": "code", "source_file": "", "source_location": ""}, {"id": "gui_simulation_interface_siminterface_init", "label": ".__init__()", "file_type": "code", "source_file": "C:\\Users\\jvele\\Documents\\_Tesis\\BrazoRobotico\\src\\gui\\simulation_interface.py", "source_location": "L17"}, {"id": "gui_simulation_interface_siminterface_setup_static_image", "label": ".__setup_static_image()", "file_type": "code", "source_file": "C:\\Users\\jvele\\Documents\\_Tesis\\BrazoRobotico\\src\\gui\\simulation_interface.py", "source_location": "L50"}, {"id": "gui_simulation_interface_siminterface_integrate_preloaded_container", "label": ".__integrate_preloaded_container()", "file_type": "code", "source_file": "C:\\Users\\jvele\\Documents\\_Tesis\\BrazoRobotico\\src\\gui\\simulation_interface.py", "source_location": "L67"}, {"id": "gui_simulation_interface_siminterface_setup_controller", "label": ".__setup_controller()", "file_type": "code", "source_file": "C:\\Users\\jvele\\Documents\\_Tesis\\BrazoRobotico\\src\\gui\\simulation_interface.py", "source_location": "L116"}, {"id": "gui_simulation_interface_siminterface_start_simulation", "label": ".start_simulation()", "file_type": "code", "source_file": "C:\\Users\\jvele\\Documents\\_Tesis\\BrazoRobotico\\src\\gui\\simulation_interface.py", "source_location": "L123"}, {"id": "gui_simulation_interface_siminterface_pause_simulation", "label": ".pause_simulation()", "file_type": "code", "source_file": "C:\\Users\\jvele\\Documents\\_Tesis\\BrazoRobotico\\src\\gui\\simulation_interface.py", "source_location": "L146"}, {"id": "gui_simulation_interface_siminterface_stop_simulation", "label": ".stop_simulation()", "file_type": "code", "source_file": "C:\\Users\\jvele\\Documents\\_Tesis\\BrazoRobotico\\src\\gui\\simulation_interface.py", "source_location": "L152"}, {"id": "gui_simulation_interface_siminterface_change_theme", "label": ".change_theme()", "file_type": "code", "source_file": "C:\\Users\\jvele\\Documents\\_Tesis\\BrazoRobotico\\src\\gui\\simulation_interface.py", "source_location": "L168"}, {"id": "gui_simulation_interface_siminterface_closeevent", "label": ".closeEvent()", "file_type": "code", "source_file": "C:\\Users\\jvele\\Documents\\_Tesis\\BrazoRobotico\\src\\gui\\simulation_interface.py", "source_location": "L177"}, {"id": "gui_simulation_interface_rationale_14", "label": "Clase encargada del modelo 3d usando contenedor completamente precargado", "file_type": "rationale", "source_file": "C:\\Users\\jvele\\Documents\\_Tesis\\BrazoRobotico\\src\\gui\\simulation_interface.py", "source_location": "L14"}, {"id": "gui_simulation_interface_rationale_51", "label": "Configura la imagen est\u00e1tica que se muestra cuando no hay simulaci\u00f3n", "file_type": "rationale", "source_file": "C:\\Users\\jvele\\Documents\\_Tesis\\BrazoRobotico\\src\\gui\\simulation_interface.py", "source_location": "L51"}, {"id": "gui_simulation_interface_rationale_68", "label": "Integra el contenedor completamente precargado en la interfaz", "file_type": "rationale", "source_file": "C:\\Users\\jvele\\Documents\\_Tesis\\BrazoRobotico\\src\\gui\\simulation_interface.py", "source_location": "L68"}, {"id": "gui_simulation_interface_rationale_124", "label": "Inicia la simulaci\u00f3n con recursos ya precargados", "file_type": "rationale", "source_file": "C:\\Users\\jvele\\Documents\\_Tesis\\BrazoRobotico\\src\\gui\\simulation_interface.py", "source_location": "L124"}], "edges": [{"source": "c_users_jvele_documents_tesis_brazorobotico_src_gui_simulation_interface_py", "target": "os", "relation": "imports", "context": "import", "confidence": "EXTRACTED", "source_file": "C:\\Users\\jvele\\Documents\\_Tesis\\BrazoRobotico\\src\\gui\\simulation_interface.py", "source_location": "L1", "weight": 1.0}, {"source": "c_users_jvele_documents_tesis_brazorobotico_src_gui_simulation_interface_py", "target": "pyqt6_qtgui", "relation": "imports_from", "context": "import", "confidence": "EXTRACTED", "source_file": "C:\\Users\\jvele\\Documents\\_Tesis\\BrazoRobotico\\src\\gui\\simulation_interface.py", "source_location": "L2", "weight": 1.0}, {"source": "c_users_jvele_documents_tesis_brazorobotico_src_gui_simulation_interface_py", "target": "pyqt6_qtquick", "relation": "imports_from", "context": "import", "confidence": "EXTRACTED", "source_file": "C:\\Users\\jvele\\Documents\\_Tesis\\BrazoRobotico\\src\\gui\\simulation_interface.py", "source_location": "L3", "weight": 1.0}, {"source": "c_users_jvele_documents_tesis_brazorobotico_src_gui_simulation_interface_py", "target": "pyqt6_qtcore", "relation": "imports_from", "context": "import", "confidence": "EXTRACTED", "source_file": "C:\\Users\\jvele\\Documents\\_Tesis\\BrazoRobotico\\src\\gui\\simulation_interface.py", "source_location": "L4", "weight": 1.0}, {"source": "c_users_jvele_documents_tesis_brazorobotico_src_gui_simulation_interface_py", "target": "pyqt6_qtwidgets", "relation": "imports_from", "context": "import", "confidence": "EXTRACTED", "source_file": "C:\\Users\\jvele\\Documents\\_Tesis\\BrazoRobotico\\src\\gui\\simulation_interface.py", "source_location": "L5", "weight": 1.0}, {"source": "c_users_jvele_documents_tesis_brazorobotico_src_gui_simulation_interface_py", "target": "data", "relation": "imports_from", "context": "import", "confidence": "EXTRACTED", "source_file": "C:\\Users\\jvele\\Documents\\_Tesis\\BrazoRobotico\\src\\gui\\simulation_interface.py", "source_location": "L6", "weight": 1.0}, {"source": "c_users_jvele_documents_tesis_brazorobotico_src_gui_simulation_interface_py", "target": "simulation", "relation": "imports_from", "context": "import", "confidence": "EXTRACTED", "source_file": "C:\\Users\\jvele\\Documents\\_Tesis\\BrazoRobotico\\src\\gui\\simulation_interface.py", "source_location": "L7", "weight": 1.0}, {"source": "c_users_jvele_documents_tesis_brazorobotico_src_gui_simulation_interface_py", "target": "gui_main_window_image_utils_mixin", "relation": "imports_from", "context": "import", "confidence": "EXTRACTED", "source_file": "C:\\Users\\jvele\\Documents\\_Tesis\\BrazoRobotico\\src\\gui\\simulation_interface.py", "source_location": "L8", "weight": 1.0}, {"source": "c_users_jvele_documents_tesis_brazorobotico_src_gui_simulation_interface_py", "target": "gui_main_window_main_theme_mixin", "relation": "imports_from", "context": "import", "confidence": "EXTRACTED", "source_file": "C:\\Users\\jvele\\Documents\\_Tesis\\BrazoRobotico\\src\\gui\\simulation_interface.py", "source_location": "L9", "weight": 1.0}, {"source": "c_users_jvele_documents_tesis_brazorobotico_src_gui_simulation_interface_py", "target": "gui_simulation_worker", "relation": "imports_from", "context": "import", "confidence": "EXTRACTED", "source_file": "C:\\Users\\jvele\\Documents\\_Tesis\\BrazoRobotico\\src\\gui\\simulation_interface.py", "source_location": "L10", "weight": 1.0}, {"source": "c_users_jvele_documents_tesis_brazorobotico_src_gui_simulation_interface_py", "target": "gui_simulation_interface_siminterface", "relation": "contains", "confidence": "EXTRACTED", "source_file": "C:\\Users\\jvele\\Documents\\_Tesis\\BrazoRobotico\\src\\gui\\simulation_interface.py", "source_location": "L13", "weight": 1.0}, {"source": "gui_simulation_interface_siminterface", "target": "imageutilsmixin", "relation": "inherits", "confidence": "EXTRACTED", "source_file": "C:\\Users\\jvele\\Documents\\_Tesis\\BrazoRobotico\\src\\gui\\simulation_interface.py", "source_location": "L13", "weight": 1.0}, {"source": "gui_simulation_interface_siminterface", "target": "gui_simulation_interface_siminterface_init", "relation": "method", "confidence": "EXTRACTED", "source_file": "C:\\Users\\jvele\\Documents\\_Tesis\\BrazoRobotico\\src\\gui\\simulation_interface.py", "source_location": "L17", "weight": 1.0}, {"source": "gui_simulation_interface_siminterface", "target": "gui_simulation_interface_siminterface_setup_static_image", "relation": "method", "confidence": "EXTRACTED", "source_file": "C:\\Users\\jvele\\Documents\\_Tesis\\BrazoRobotico\\src\\gui\\simulation_interface.py", "source_location": "L50", "weight": 1.0}, {"source": "gui_simulation_interface_siminterface", "target": "gui_simulation_interface_siminterface_integrate_preloaded_container", "relation": "method", "confidence": "EXTRACTED", "source_file": "C:\\Users\\jvele\\Documents\\_Tesis\\BrazoRobotico\\src\\gui\\simulation_interface.py", "source_location": "L67", "weight": 1.0}, {"source": "gui_simulation_interface_siminterface", "target": "gui_simulation_interface_siminterface_setup_controller", "relation": "method", "confidence": "EXTRACTED", "source_file": "C:\\Users\\jvele\\Documents\\_Tesis\\BrazoRobotico\\src\\gui\\simulation_interface.py", "source_location": "L116", "weight": 1.0}, {"source": "gui_simulation_interface_siminterface", "target": "gui_simulation_interface_siminterface_start_simulation", "relation": "method", "confidence": "EXTRACTED", "source_file": "C:\\Users\\jvele\\Documents\\_Tesis\\BrazoRobotico\\src\\gui\\simulation_interface.py", "source_location": "L123", "weight": 1.0}, {"source": "gui_simulation_interface_siminterface", "target": "gui_simulation_interface_siminterface_pause_simulation", "relation": "method", "confidence": "EXTRACTED", "source_file": "C:\\Users\\jvele\\Documents\\_Tesis\\BrazoRobotico\\src\\gui\\simulation_interface.py", "source_location": "L146", "weight": 1.0}, {"source": "gui_simulation_interface_siminterface", "target": "gui_simulation_interface_siminterface_stop_simulation", "relation": "method", "confidence": "EXTRACTED", "source_file": "C:\\Users\\jvele\\Documents\\_Tesis\\BrazoRobotico\\src\\gui\\simulation_interface.py", "source_location": "L152", "weight": 1.0}, {"source": "gui_simulation_interface_siminterface", "target": "gui_simulation_interface_siminterface_change_theme", "relation": "method", "confidence": "EXTRACTED", "source_file": "C:\\Users\\jvele\\Documents\\_Tesis\\BrazoRobotico\\src\\gui\\simulation_interface.py", "source_location": "L168", "weight": 1.0}, {"source": "gui_simulation_interface_siminterface", "target": "gui_simulation_interface_siminterface_closeevent", "relation": "method", "confidence": "EXTRACTED", "source_file": "C:\\Users\\jvele\\Documents\\_Tesis\\BrazoRobotico\\src\\gui\\simulation_interface.py", "source_location": "L177", "weight": 1.0}, {"source": "gui_simulation_interface_siminterface_init", "target": "gui_simulation_interface_siminterface_setup_static_image", "relation": "calls", "context": "call", "confidence": "EXTRACTED", "source_file": "C:\\Users\\jvele\\Documents\\_Tesis\\BrazoRobotico\\src\\gui\\simulation_interface.py", "source_location": "L44", "weight": 1.0}, {"source": "gui_simulation_interface_siminterface_init", "target": "gui_simulation_interface_siminterface_integrate_preloaded_container", "relation": "calls", "context": "call", "confidence": "EXTRACTED", "source_file": "C:\\Users\\jvele\\Documents\\_Tesis\\BrazoRobotico\\src\\gui\\simulation_interface.py", "source_location": "L47", "weight": 1.0}, {"source": "gui_simulation_interface_siminterface_init", "target": "gui_simulation_interface_siminterface_setup_controller", "relation": "calls", "context": "call", "confidence": "EXTRACTED", "source_file": "C:\\Users\\jvele\\Documents\\_Tesis\\BrazoRobotico\\src\\gui\\simulation_interface.py", "source_location": "L48", "weight": 1.0}, {"source": "gui_simulation_interface_siminterface_closeevent", "target": "gui_simulation_interface_siminterface_stop_simulation", "relation": "calls", "context": "call", "confidence": "EXTRACTED", "source_file": "C:\\Users\\jvele\\Documents\\_Tesis\\BrazoRobotico\\src\\gui\\simulation_interface.py", "source_location": "L181", "weight": 1.0}, {"source": "gui_simulation_interface_rationale_14", "target": "gui_simulation_interface_siminterface", "relation": "rationale_for", "confidence": "EXTRACTED", "source_file": "C:\\Users\\jvele\\Documents\\_Tesis\\BrazoRobotico\\src\\gui\\simulation_interface.py", "source_location": "L14", "weight": 1.0}, {"source": "gui_simulation_interface_rationale_51", "target": "gui_simulation_interface_siminterface_setup_static_image", "relation": "rationale_for", "confidence": "EXTRACTED", "source_file": "C:\\Users\\jvele\\Documents\\_Tesis\\BrazoRobotico\\src\\gui\\simulation_interface.py", "source_location": "L51", "weight": 1.0}, {"source": "gui_simulation_interface_rationale_68", "target": "gui_simulation_interface_siminterface_integrate_preloaded_container", "relation": "rationale_for", "confidence": "EXTRACTED", "source_file": "C:\\Users\\jvele\\Documents\\_Tesis\\BrazoRobotico\\src\\gui\\simulation_interface.py", "source_location": "L68", "weight": 1.0}, {"source": "gui_simulation_interface_rationale_124", "target": "gui_simulation_interface_siminterface_start_simulation", "relation": "rationale_for", "confidence": "EXTRACTED", "source_file": "C:\\Users\\jvele\\Documents\\_Tesis\\BrazoRobotico\\src\\gui\\simulation_interface.py", "source_location": "L124", "weight": 1.0}], "raw_calls": [{"caller_nid": "gui_simulation_interface_siminterface_init", "callee": "super", "is_member_call": false, "source_file": "C:\\Users\\jvele\\Documents\\_Tesis\\BrazoRobotico\\src\\gui\\simulation_interface.py", "source_location": "L18"}, {"caller_nid": "gui_simulation_interface_siminterface_init", "callee": "print", "is_member_call": false, "source_file": "C:\\Users\\jvele\\Documents\\_Tesis\\BrazoRobotico\\src\\gui\\simulation_interface.py", "source_location": "L31"}, {"caller_nid": "gui_simulation_interface_siminterface_init", "callee": "layout", "is_member_call": true, "source_file": "C:\\Users\\jvele\\Documents\\_Tesis\\BrazoRobotico\\src\\gui\\simulation_interface.py", "source_location": "L34"}, {"caller_nid": "gui_simulation_interface_siminterface_init", "callee": "QVBoxLayout", "is_member_call": false, "source_file": "C:\\Users\\jvele\\Documents\\_Tesis\\BrazoRobotico\\src\\gui\\simulation_interface.py", "source_location": "L35"}, {"caller_nid": "gui_simulation_interface_siminterface_init", "callee": "setContentsMargins", "is_member_call": true, "source_file": "C:\\Users\\jvele\\Documents\\_Tesis\\BrazoRobotico\\src\\gui\\simulation_interface.py", "source_location": "L36"}, {"caller_nid": "gui_simulation_interface_siminterface_init", "callee": "setLayout", "is_member_call": true, "source_file": "C:\\Users\\jvele\\Documents\\_Tesis\\BrazoRobotico\\src\\gui\\simulation_interface.py", "source_location": "L37"}, {"caller_nid": "gui_simulation_interface_siminterface_init", "callee": "setSizePolicy", "is_member_call": true, "source_file": "C:\\Users\\jvele\\Documents\\_Tesis\\BrazoRobotico\\src\\gui\\simulation_interface.py", "source_location": "L39"}, {"caller_nid": "gui_simulation_interface_siminterface_init", "callee": "setMinimumSize", "is_member_call": true, "source_file": "C:\\Users\\jvele\\Documents\\_Tesis\\BrazoRobotico\\src\\gui\\simulation_interface.py", "source_location": "L41"}, {"caller_nid": "gui_simulation_interface_siminterface_setup_static_image", "callee": "join", "is_member_call": true, "source_file": "C:\\Users\\jvele\\Documents\\_Tesis\\BrazoRobotico\\src\\gui\\simulation_interface.py", "source_location": "L52"}, {"caller_nid": "gui_simulation_interface_siminterface_setup_static_image", "callee": "dirname", "is_member_call": true, "source_file": "C:\\Users\\jvele\\Documents\\_Tesis\\BrazoRobotico\\src\\gui\\simulation_interface.py", "source_location": "L52"}, {"caller_nid": "gui_simulation_interface_siminterface_setup_static_image", "callee": "join", "is_member_call": true, "source_file": "C:\\Users\\jvele\\Documents\\_Tesis\\BrazoRobotico\\src\\gui\\simulation_interface.py", "source_location": "L54"}, {"caller_nid": "gui_simulation_interface_siminterface_setup_static_image", "callee": "dirname", "is_member_call": true, "source_file": "C:\\Users\\jvele\\Documents\\_Tesis\\BrazoRobotico\\src\\gui\\simulation_interface.py", "source_location": "L54"}, {"caller_nid": "gui_simulation_interface_siminterface_setup_static_image", "callee": "QPixmap", "is_member_call": false, "source_file": "C:\\Users\\jvele\\Documents\\_Tesis\\BrazoRobotico\\src\\gui\\simulation_interface.py", "source_location": "L56"}, {"caller_nid": "gui_simulation_interface_siminterface_setup_static_image", "callee": "QLabel", "is_member_call": false, "source_file": "C:\\Users\\jvele\\Documents\\_Tesis\\BrazoRobotico\\src\\gui\\simulation_interface.py", "source_location": "L57"}, {"caller_nid": "gui_simulation_interface_siminterface_setup_static_image", "callee": "setAlignment", "is_member_call": true, "source_file": "C:\\Users\\jvele\\Documents\\_Tesis\\BrazoRobotico\\src\\gui\\simulation_interface.py", "source_location": "L58"}, {"caller_nid": "gui_simulation_interface_siminterface_setup_static_image", "callee": "setSizePolicy", "is_member_call": true, "source_file": "C:\\Users\\jvele\\Documents\\_Tesis\\BrazoRobotico\\src\\gui\\simulation_interface.py", "source_location": "L59"}, {"caller_nid": "gui_simulation_interface_siminterface_setup_static_image", "callee": "setMinimumSize", "is_member_call": true, "source_file": "C:\\Users\\jvele\\Documents\\_Tesis\\BrazoRobotico\\src\\gui\\simulation_interface.py", "source_location": "L61"}, {"caller_nid": "gui_simulation_interface_siminterface_setup_static_image", "callee": "addWidget", "is_member_call": true, "source_file": "C:\\Users\\jvele\\Documents\\_Tesis\\BrazoRobotico\\src\\gui\\simulation_interface.py", "source_location": "L62"}, {"caller_nid": "gui_simulation_interface_siminterface_setup_static_image", "callee": "layout", "is_member_call": true, "source_file": "C:\\Users\\jvele\\Documents\\_Tesis\\BrazoRobotico\\src\\gui\\simulation_interface.py", "source_location": "L62"}, {"caller_nid": "gui_simulation_interface_siminterface_setup_static_image", "callee": "set_static_image", "is_member_call": true, "source_file": "C:\\Users\\jvele\\Documents\\_Tesis\\BrazoRobotico\\src\\gui\\simulation_interface.py", "source_location": "L63"}, {"caller_nid": "gui_simulation_interface_siminterface_setup_static_image", "callee": "get_instance", "is_member_call": true, "source_file": "C:\\Users\\jvele\\Documents\\_Tesis\\BrazoRobotico\\src\\gui\\simulation_interface.py", "source_location": "L64"}, {"caller_nid": "gui_simulation_interface_siminterface_setup_static_image", "callee": "connect", "is_member_call": true, "source_file": "C:\\Users\\jvele\\Documents\\_Tesis\\BrazoRobotico\\src\\gui\\simulation_interface.py", "source_location": "L65"}, {"caller_nid": "gui_simulation_interface_siminterface_integrate_preloaded_container", "callee": "print", "is_member_call": false, "source_file": "C:\\Users\\jvele\\Documents\\_Tesis\\BrazoRobotico\\src\\gui\\simulation_interface.py", "source_location": "L71"}, {"caller_nid": "gui_simulation_interface_siminterface_integrate_preloaded_container", "callee": "createWindowContainer", "is_member_call": true, "source_file": "C:\\Users\\jvele\\Documents\\_Tesis\\BrazoRobotico\\src\\gui\\simulation_interface.py", "source_location": "L74"}, {"caller_nid": "gui_simulation_interface_siminterface_integrate_preloaded_container", "callee": "setParent", "is_member_call": true, "source_file": "C:\\Users\\jvele\\Documents\\_Tesis\\BrazoRobotico\\src\\gui\\simulation_interface.py", "source_location": "L80"}, {"caller_nid": "gui_simulation_interface_siminterface_integrate_preloaded_container", "callee": "setSizePolicy", "is_member_call": true, "source_file": "C:\\Users\\jvele\\Documents\\_Tesis\\BrazoRobotico\\src\\gui\\simulation_interface.py", "source_location": "L83"}, {"caller_nid": "gui_simulation_interface_siminterface_integrate_preloaded_container", "callee": "setMinimumSize", "is_member_call": true, "source_file": "C:\\Users\\jvele\\Documents\\_Tesis\\BrazoRobotico\\src\\gui\\simulation_interface.py", "source_location": "L87"}, {"caller_nid": "gui_simulation_interface_siminterface_integrate_preloaded_container", "callee": "addWidget", "is_member_call": true, "source_file": "C:\\Users\\jvele\\Documents\\_Tesis\\BrazoRobotico\\src\\gui\\simulation_interface.py", "source_location": "L90"}, {"caller_nid": "gui_simulation_interface_siminterface_integrate_preloaded_container", "callee": "layout", "is_member_call": true, "source_file": "C:\\Users\\jvele\\Documents\\_Tesis\\BrazoRobotico\\src\\gui\\simulation_interface.py", "source_location": "L90"}, {"caller_nid": "gui_simulation_interface_siminterface_integrate_preloaded_container", "callee": "hide", "is_member_call": true, "source_file": "C:\\Users\\jvele\\Documents\\_Tesis\\BrazoRobotico\\src\\gui\\simulation_interface.py", "source_location": "L93"}, {"caller_nid": "gui_simulation_interface_siminterface_integrate_preloaded_container", "callee": "setFlags", "is_member_call": true, "source_file": "C:\\Users\\jvele\\Documents\\_Tesis\\BrazoRobotico\\src\\gui\\simulation_interface.py", "source_location": "L97"}, {"caller_nid": "gui_simulation_interface_siminterface_integrate_preloaded_container", "callee": "setResizeMode", "is_member_call": true, "source_file": "C:\\Users\\jvele\\Documents\\_Tesis\\BrazoRobotico\\src\\gui\\simulation_interface.py", "source_location": "L100"}, {"caller_nid": "gui_simulation_interface_siminterface_integrate_preloaded_container", "callee": "print", "is_member_call": false, "source_file": "C:\\Users\\jvele\\Documents\\_Tesis\\BrazoRobotico\\src\\gui\\simulation_interface.py", "source_location": "L103"}, {"caller_nid": "gui_simulation_interface_siminterface_integrate_preloaded_container", "callee": "rootObject", "is_member_call": true, "source_file": "C:\\Users\\jvele\\Documents\\_Tesis\\BrazoRobotico\\src\\gui\\simulation_interface.py", "source_location": "L106"}, {"caller_nid": "gui_simulation_interface_siminterface_integrate_preloaded_container", "callee": "SimWorker", "is_member_call": false, "source_file": "C:\\Users\\jvele\\Documents\\_Tesis\\BrazoRobotico\\src\\gui\\simulation_interface.py", "source_location": "L108"}, {"caller_nid": "gui_simulation_interface_siminterface_integrate_preloaded_container", "callee": "start", "is_member_call": true, "source_file": "C:\\Users\\jvele\\Documents\\_Tesis\\BrazoRobotico\\src\\gui\\simulation_interface.py", "source_location": "L109"}, {"caller_nid": "gui_simulation_interface_siminterface_integrate_preloaded_container", "callee": "print", "is_member_call": false, "source_file": "C:\\Users\\jvele\\Documents\\_Tesis\\BrazoRobotico\\src\\gui\\simulation_interface.py", "source_location": "L111"}, {"caller_nid": "gui_simulation_interface_siminterface_integrate_preloaded_container", "callee": "print", "is_member_call": false, "source_file": "C:\\Users\\jvele\\Documents\\_Tesis\\BrazoRobotico\\src\\gui\\simulation_interface.py", "source_location": "L114"}, {"caller_nid": "gui_simulation_interface_siminterface_setup_controller", "callee": "PhysicsWorker", "is_member_call": false, "source_file": "C:\\Users\\jvele\\Documents\\_Tesis\\BrazoRobotico\\src\\gui\\simulation_interface.py", "source_location": "L117"}, {"caller_nid": "gui_simulation_interface_siminterface_setup_controller", "callee": "DataFlow", "is_member_call": false, "source_file": "C:\\Users\\jvele\\Documents\\_Tesis\\BrazoRobotico\\src\\gui\\simulation_interface.py", "source_location": "L119"}, {"caller_nid": "gui_simulation_interface_siminterface_setup_controller", "callee": "start", "is_member_call": true, "source_file": "C:\\Users\\jvele\\Documents\\_Tesis\\BrazoRobotico\\src\\gui\\simulation_interface.py", "source_location": "L121"}, {"caller_nid": "gui_simulation_interface_siminterface_start_simulation", "callee": "print", "is_member_call": false, "source_file": "C:\\Users\\jvele\\Documents\\_Tesis\\BrazoRobotico\\src\\gui\\simulation_interface.py", "source_location": "L127"}, {"caller_nid": "gui_simulation_interface_siminterface_start_simulation", "callee": "hide", "is_member_call": true, "source_file": "C:\\Users\\jvele\\Documents\\_Tesis\\BrazoRobotico\\src\\gui\\simulation_interface.py", "source_location": "L131"}, {"caller_nid": "gui_simulation_interface_siminterface_start_simulation", "callee": "show", "is_member_call": true, "source_file": "C:\\Users\\jvele\\Documents\\_Tesis\\BrazoRobotico\\src\\gui\\simulation_interface.py", "source_location": "L132"}, {"caller_nid": "gui_simulation_interface_siminterface_start_simulation", "callee": "show", "is_member_call": true, "source_file": "C:\\Users\\jvele\\Documents\\_Tesis\\BrazoRobotico\\src\\gui\\simulation_interface.py", "source_location": "L133"}, {"caller_nid": "gui_simulation_interface_siminterface_start_simulation", "callee": "update", "is_member_call": true, "source_file": "C:\\Users\\jvele\\Documents\\_Tesis\\BrazoRobotico\\src\\gui\\simulation_interface.py", "source_location": "L134"}, {"caller_nid": "gui_simulation_interface_siminterface_start_simulation", "callee": "isRunning", "is_member_call": true, "source_file": "C:\\Users\\jvele\\Documents\\_Tesis\\BrazoRobotico\\src\\gui\\simulation_interface.py", "source_location": "L137"}, {"caller_nid": "gui_simulation_interface_siminterface_start_simulation", "callee": "start", "is_member_call": true, "source_file": "C:\\Users\\jvele\\Documents\\_Tesis\\BrazoRobotico\\src\\gui\\simulation_interface.py", "source_location": "L138"}, {"caller_nid": "gui_simulation_interface_siminterface_start_simulation", "callee": "start", "is_member_call": true, "source_file": "C:\\Users\\jvele\\Documents\\_Tesis\\BrazoRobotico\\src\\gui\\simulation_interface.py", "source_location": "L140"}, {"caller_nid": "gui_simulation_interface_siminterface_start_simulation", "callee": "print", "is_member_call": false, "source_file": "C:\\Users\\jvele\\Documents\\_Tesis\\BrazoRobotico\\src\\gui\\simulation_interface.py", "source_location": "L144"}, {"caller_nid": "gui_simulation_interface_siminterface_pause_simulation", "callee": "pause", "is_member_call": true, "source_file": "C:\\Users\\jvele\\Documents\\_Tesis\\BrazoRobotico\\src\\gui\\simulation_interface.py", "source_location": "L150"}, {"caller_nid": "gui_simulation_interface_siminterface_stop_simulation", "callee": "pause", "is_member_call": true, "source_file": "C:\\Users\\jvele\\Documents\\_Tesis\\BrazoRobotico\\src\\gui\\simulation_interface.py", "source_location": "L158"}, {"caller_nid": "gui_simulation_interface_siminterface_stop_simulation", "callee": "hide", "is_member_call": true, "source_file": "C:\\Users\\jvele\\Documents\\_Tesis\\BrazoRobotico\\src\\gui\\simulation_interface.py", "source_location": "L161"}, {"caller_nid": "gui_simulation_interface_siminterface_stop_simulation", "callee": "hide", "is_member_call": true, "source_file": "C:\\Users\\jvele\\Documents\\_Tesis\\BrazoRobotico\\src\\gui\\simulation_interface.py", "source_location": "L163"}, {"caller_nid": "gui_simulation_interface_siminterface_stop_simulation", "callee": "show", "is_member_call": true, "source_file": "C:\\Users\\jvele\\Documents\\_Tesis\\BrazoRobotico\\src\\gui\\simulation_interface.py", "source_location": "L165"}, {"caller_nid": "gui_simulation_interface_siminterface_stop_simulation", "callee": "set_static_image", "is_member_call": true, "source_file": "C:\\Users\\jvele\\Documents\\_Tesis\\BrazoRobotico\\src\\gui\\simulation_interface.py", "source_location": "L166"}, {"caller_nid": "gui_simulation_interface_siminterface_change_theme", "callee": "toggle_theme", "is_member_call": true, "source_file": "C:\\Users\\jvele\\Documents\\_Tesis\\BrazoRobotico\\src\\gui\\simulation_interface.py", "source_location": "L169"}, {"caller_nid": "gui_simulation_interface_siminterface_change_theme", "callee": "setProperty", "is_member_call": true, "source_file": "C:\\Users\\jvele\\Documents\\_Tesis\\BrazoRobotico\\src\\gui\\simulation_interface.py", "source_location": "L171"}, {"caller_nid": "gui_simulation_interface_siminterface_change_theme", "callee": "setProperty", "is_member_call": true, "source_file": "C:\\Users\\jvele\\Documents\\_Tesis\\BrazoRobotico\\src\\gui\\simulation_interface.py", "source_location": "L172"}, {"caller_nid": "gui_simulation_interface_siminterface_change_theme", "callee": "setProperty", "is_member_call": true, "source_file": "C:\\Users\\jvele\\Documents\\_Tesis\\BrazoRobotico\\src\\gui\\simulation_interface.py", "source_location": "L174"}, {"caller_nid": "gui_simulation_interface_siminterface_change_theme", "callee": "setProperty", "is_member_call": true, "source_file": "C:\\Users\\jvele\\Documents\\_Tesis\\BrazoRobotico\\src\\gui\\simulation_interface.py", "source_location": "L175"}, {"caller_nid": "gui_simulation_interface_siminterface_closeevent", "callee": "isRunning", "is_member_call": true, "source_file": "C:\\Users\\jvele\\Documents\\_Tesis\\BrazoRobotico\\src\\gui\\simulation_interface.py", "source_location": "L185"}, {"caller_nid": "gui_simulation_interface_siminterface_closeevent", "callee": "quit", "is_member_call": true, "source_file": "C:\\Users\\jvele\\Documents\\_Tesis\\BrazoRobotico\\src\\gui\\simulation_interface.py", "source_location": "L186"}, {"caller_nid": "gui_simulation_interface_siminterface_closeevent", "callee": "wait", "is_member_call": true, "source_file": "C:\\Users\\jvele\\Documents\\_Tesis\\BrazoRobotico\\src\\gui\\simulation_interface.py", "source_location": "L187"}, {"caller_nid": "gui_simulation_interface_siminterface_closeevent", "callee": "print", "is_member_call": false, "source_file": "C:\\Users\\jvele\\Documents\\_Tesis\\BrazoRobotico\\src\\gui\\simulation_interface.py", "source_location": "L189"}, {"caller_nid": "gui_simulation_interface_siminterface_closeevent", "callee": "super", "is_member_call": false, "source_file": "C:\\Users\\jvele\\Documents\\_Tesis\\BrazoRobotico\\src\\gui\\simulation_interface.py", "source_location": "L196"}]}