{"nodes": [{"id": "c_users_jvele_documents_tesis_brazorobotico_src_gui_kinematics_worker_py", "label": "kinematics_worker.py", "file_type": "code", "source_file": "C:\\Users\\jvele\\Documents\\_Tesis\\BrazoRobotico\\src\\gui\\kinematics_worker.py", "source_location": "L1"}, {"id": "gui_kinematics_worker_kinematicsworker", "label": "KinematicsWorker", "file_type": "code", "source_file": "C:\\Users\\jvele\\Documents\\_Tesis\\BrazoRobotico\\src\\gui\\kinematics_worker.py", "source_location": "L16"}, {"id": "qthread", "label": "QThread", "file_type": "code", "source_file": "", "source_location": ""}, {"id": "gui_kinematics_worker_kinematicsworker_init", "label": ".__init__()", "file_type": "code", "source_file": "C:\\Users\\jvele\\Documents\\_Tesis\\BrazoRobotico\\src\\gui\\kinematics_worker.py", "source_location": "L21"}, {"id": "gui_kinematics_worker_kinematicsworker_h_dh", "label": ".h_dh()", "file_type": "code", "source_file": "C:\\Users\\jvele\\Documents\\_Tesis\\BrazoRobotico\\src\\gui\\kinematics_worker.py", "source_location": "L40"}, {"id": "gui_kinematics_worker_kinematicsworker_hrx", "label": ".hrx()", "file_type": "code", "source_file": "C:\\Users\\jvele\\Documents\\_Tesis\\BrazoRobotico\\src\\gui\\kinematics_worker.py", "source_location": "L45"}, {"id": "gui_kinematics_worker_kinematicsworker_hrz", "label": ".hrz()", "file_type": "code", "source_file": "C:\\Users\\jvele\\Documents\\_Tesis\\BrazoRobotico\\src\\gui\\kinematics_worker.py", "source_location": "L49"}, {"id": "gui_kinematics_worker_kinematicsworker_htx", "label": ".htx()", "file_type": "code", "source_file": "C:\\Users\\jvele\\Documents\\_Tesis\\BrazoRobotico\\src\\gui\\kinematics_worker.py", "source_location": "L53"}, {"id": "gui_kinematics_worker_kinematicsworker_htz", "label": ".htz()", "file_type": "code", "source_file": "C:\\Users\\jvele\\Documents\\_Tesis\\BrazoRobotico\\src\\gui\\kinematics_worker.py", "source_location": "L56"}, {"id": "gui_kinematics_worker_kinematicsworker_t_matrices", "label": ".t_matrices()", "file_type": "code", "source_file": "C:\\Users\\jvele\\Documents\\_Tesis\\BrazoRobotico\\src\\gui\\kinematics_worker.py", "source_location": "L59"}, {"id": "gui_kinematics_worker_kinematicsworker_cd", "label": ".cd()", "file_type": "code", "source_file": "C:\\Users\\jvele\\Documents\\_Tesis\\BrazoRobotico\\src\\gui\\kinematics_worker.py", "source_location": "L72"}, {"id": "gui_kinematics_worker_kinematicsworker_jacobiano_analitico", "label": ".jacobiano_analitico()", "file_type": "code", "source_file": "C:\\Users\\jvele\\Documents\\_Tesis\\BrazoRobotico\\src\\gui\\kinematics_worker.py", "source_location": "L77"}, {"id": "gui_kinematics_worker_kinematicsworker_ci", "label": ".ci()", "file_type": "code", "source_file": "C:\\Users\\jvele\\Documents\\_Tesis\\BrazoRobotico\\src\\gui\\kinematics_worker.py", "source_location": "L90"}, {"id": "gui_kinematics_worker_kinematicsworker_set_target", "label": ".set_target()", "file_type": "code", "source_file": "C:\\Users\\jvele\\Documents\\_Tesis\\BrazoRobotico\\src\\gui\\kinematics_worker.py", "source_location": "L115"}, {"id": "gui_kinematics_worker_kinematicsworker_update_sensor_data", "label": ".update_sensor_data()", "file_type": "code", "source_file": "C:\\Users\\jvele\\Documents\\_Tesis\\BrazoRobotico\\src\\gui\\kinematics_worker.py", "source_location": "L131"}, {"id": "gui_kinematics_worker_rationale_1", "label": "m\u00f3dulo de c\u00e1lculo de cinem\u00e1tica inversa y realimentada.     La clase Kinematic", "file_type": "rationale", "source_file": "C:\\Users\\jvele\\Documents\\_Tesis\\BrazoRobotico\\src\\gui\\kinematics_worker.py", "source_location": "L1"}, {"id": "gui_kinematics_worker_rationale_116", "label": "Define el objetivo cartesiano hacia el cual debe converger            el algori", "file_type": "rationale", "source_file": "C:\\Users\\jvele\\Documents\\_Tesis\\BrazoRobotico\\src\\gui\\kinematics_worker.py", "source_location": "L116"}, {"id": "gui_kinematics_worker_rationale_132", "label": "Slot conectado a PhysicalSignalManager.data_received. Cada vez que            e", "file_type": "rationale", "source_file": "C:\\Users\\jvele\\Documents\\_Tesis\\BrazoRobotico\\src\\gui\\kinematics_worker.py", "source_location": "L132"}], "edges": [{"source": "c_users_jvele_documents_tesis_brazorobotico_src_gui_kinematics_worker_py", "target": "numpy", "relation": "imports", "context": "import", "confidence": "EXTRACTED", "source_file": "C:\\Users\\jvele\\Documents\\_Tesis\\BrazoRobotico\\src\\gui\\kinematics_worker.py", "source_location": "L12", "weight": 1.0}, {"source": "c_users_jvele_documents_tesis_brazorobotico_src_gui_kinematics_worker_py", "target": "pyqt6_qtcore", "relation": "imports_from", "context": "import", "confidence": "EXTRACTED", "source_file": "C:\\Users\\jvele\\Documents\\_Tesis\\BrazoRobotico\\src\\gui\\kinematics_worker.py", "source_location": "L13", "weight": 1.0}, {"source": "c_users_jvele_documents_tesis_brazorobotico_src_gui_kinematics_worker_py", "target": "gui_kinematics_worker_kinematicsworker", "relation": "contains", "confidence": "EXTRACTED", "source_file": "C:\\Users\\jvele\\Documents\\_Tesis\\BrazoRobotico\\src\\gui\\kinematics_worker.py", "source_location": "L16", "weight": 1.0}, {"source": "gui_kinematics_worker_kinematicsworker", "target": "qthread", "relation": "inherits", "confidence": "EXTRACTED", "source_file": "C:\\Users\\jvele\\Documents\\_Tesis\\BrazoRobotico\\src\\gui\\kinematics_worker.py", "source_location": "L16", "weight": 1.0}, {"source": "c_users_jvele_documents_tesis_brazorobotico_src_gui_kinematics_worker_py", "target": "pyqt6_qtcore", "relation": "imports_from", "context": "import", "confidence": "EXTRACTED", "source_file": "C:\\Users\\jvele\\Documents\\_Tesis\\BrazoRobotico\\src\\gui\\kinematics_worker.py", "source_location": "L18", "weight": 1.0}, {"source": "gui_kinematics_worker_kinematicsworker", "target": "gui_kinematics_worker_kinematicsworker_init", "relation": "method", "confidence": "EXTRACTED", "source_file": "C:\\Users\\jvele\\Documents\\_Tesis\\BrazoRobotico\\src\\gui\\kinematics_worker.py", "source_location": "L21", "weight": 1.0}, {"source": "gui_kinematics_worker_kinematicsworker", "target": "gui_kinematics_worker_kinematicsworker_h_dh", "relation": "method", "confidence": "EXTRACTED", "source_file": "C:\\Users\\jvele\\Documents\\_Tesis\\BrazoRobotico\\src\\gui\\kinematics_worker.py", "source_location": "L40", "weight": 1.0}, {"source": "gui_kinematics_worker_kinematicsworker", "target": "gui_kinematics_worker_kinematicsworker_hrx", "relation": "method", "confidence": "EXTRACTED", "source_file": "C:\\Users\\jvele\\Documents\\_Tesis\\BrazoRobotico\\src\\gui\\kinematics_worker.py", "source_location": "L45", "weight": 1.0}, {"source": "gui_kinematics_worker_kinematicsworker", "target": "gui_kinematics_worker_kinematicsworker_hrz", "relation": "method", "confidence": "EXTRACTED", "source_file": "C:\\Users\\jvele\\Documents\\_Tesis\\BrazoRobotico\\src\\gui\\kinematics_worker.py", "source_location": "L49", "weight": 1.0}, {"source": "gui_kinematics_worker_kinematicsworker", "target": "gui_kinematics_worker_kinematicsworker_htx", "relation": "method", "confidence": "EXTRACTED", "source_file": "C:\\Users\\jvele\\Documents\\_Tesis\\BrazoRobotico\\src\\gui\\kinematics_worker.py", "source_location": "L53", "weight": 1.0}, {"source": "gui_kinematics_worker_kinematicsworker", "target": "gui_kinematics_worker_kinematicsworker_htz", "relation": "method", "confidence": "EXTRACTED", "source_file": "C:\\Users\\jvele\\Documents\\_Tesis\\BrazoRobotico\\src\\gui\\kinematics_worker.py", "source_location": "L56", "weight": 1.0}, {"source": "gui_kinematics_worker_kinematicsworker", "target": "gui_kinematics_worker_kinematicsworker_t_matrices", "relation": "method", "confidence": "EXTRACTED", "source_file": "C:\\Users\\jvele\\Documents\\_Tesis\\BrazoRobotico\\src\\gui\\kinematics_worker.py", "source_location": "L59", "weight": 1.0}, {"source": "gui_kinematics_worker_kinematicsworker", "target": "gui_kinematics_worker_kinematicsworker_cd", "relation": "method", "confidence": "EXTRACTED", "source_file": "C:\\Users\\jvele\\Documents\\_Tesis\\BrazoRobotico\\src\\gui\\kinematics_worker.py", "source_location": "L72", "weight": 1.0}, {"source": "gui_kinematics_worker_kinematicsworker", "target": "gui_kinematics_worker_kinematicsworker_jacobiano_analitico", "relation": "method", "confidence": "EXTRACTED", "source_file": "C:\\Users\\jvele\\Documents\\_Tesis\\BrazoRobotico\\src\\gui\\kinematics_worker.py", "source_location": "L77", "weight": 1.0}, {"source": "gui_kinematics_worker_kinematicsworker", "target": "gui_kinematics_worker_kinematicsworker_ci", "relation": "method", "confidence": "EXTRACTED", "source_file": "C:\\Users\\jvele\\Documents\\_Tesis\\BrazoRobotico\\src\\gui\\kinematics_worker.py", "source_location": "L90", "weight": 1.0}, {"source": "gui_kinematics_worker_kinematicsworker", "target": "gui_kinematics_worker_kinematicsworker_set_target", "relation": "method", "confidence": "EXTRACTED", "source_file": "C:\\Users\\jvele\\Documents\\_Tesis\\BrazoRobotico\\src\\gui\\kinematics_worker.py", "source_location": "L115", "weight": 1.0}, {"source": "gui_kinematics_worker_kinematicsworker", "target": "gui_kinematics_worker_kinematicsworker_update_sensor_data", "relation": "method", "confidence": "EXTRACTED", "source_file": "C:\\Users\\jvele\\Documents\\_Tesis\\BrazoRobotico\\src\\gui\\kinematics_worker.py", "source_location": "L131", "weight": 1.0}, {"source": "gui_kinematics_worker_kinematicsworker_t_matrices", "target": "gui_kinematics_worker_kinematicsworker_hrz", "relation": "calls", "context": "call", "confidence": "EXTRACTED", "source_file": "C:\\Users\\jvele\\Documents\\_Tesis\\BrazoRobotico\\src\\gui\\kinematics_worker.py", "source_location": "L60", "weight": 1.0}, {"source": "gui_kinematics_worker_kinematicsworker_t_matrices", "target": "gui_kinematics_worker_kinematicsworker_htz", "relation": "calls", "context": "call", "confidence": "EXTRACTED", "source_file": "C:\\Users\\jvele\\Documents\\_Tesis\\BrazoRobotico\\src\\gui\\kinematics_worker.py", "source_location": "L61", "weight": 1.0}, {"source": "gui_kinematics_worker_kinematicsworker_t_matrices", "target": "gui_kinematics_worker_kinematicsworker_htx", "relation": "calls", "context": "call", "confidence": "EXTRACTED", "source_file": "C:\\Users\\jvele\\Documents\\_Tesis\\BrazoRobotico\\src\\gui\\kinematics_worker.py", "source_location": "L61", "weight": 1.0}, {"source": "gui_kinematics_worker_kinematicsworker_t_matrices", "target": "gui_kinematics_worker_kinematicsworker_hrx", "relation": "calls", "context": "call", "confidence": "EXTRACTED", "source_file": "C:\\Users\\jvele\\Documents\\_Tesis\\BrazoRobotico\\src\\gui\\kinematics_worker.py", "source_location": "L61", "weight": 1.0}, {"source": "gui_kinematics_worker_kinematicsworker_cd", "target": "gui_kinematics_worker_kinematicsworker_t_matrices", "relation": "calls", "context": "call", "confidence": "EXTRACTED", "source_file": "C:\\Users\\jvele\\Documents\\_Tesis\\BrazoRobotico\\src\\gui\\kinematics_worker.py", "source_location": "L73", "weight": 1.0}, {"source": "gui_kinematics_worker_kinematicsworker_cd", "target": "gui_kinematics_worker_kinematicsworker_h_dh", "relation": "calls", "context": "call", "confidence": "EXTRACTED", "source_file": "C:\\Users\\jvele\\Documents\\_Tesis\\BrazoRobotico\\src\\gui\\kinematics_worker.py", "source_location": "L74", "weight": 1.0}, {"source": "gui_kinematics_worker_kinematicsworker_jacobiano_analitico", "target": "gui_kinematics_worker_kinematicsworker_t_matrices", "relation": "calls", "context": "call", "confidence": "EXTRACTED", "source_file": "C:\\Users\\jvele\\Documents\\_Tesis\\BrazoRobotico\\src\\gui\\kinematics_worker.py", "source_location": "L79", "weight": 1.0}, {"source": "gui_kinematics_worker_kinematicsworker_ci", "target": "gui_kinematics_worker_kinematicsworker_cd", "relation": "calls", "context": "call", "confidence": "EXTRACTED", "source_file": "C:\\Users\\jvele\\Documents\\_Tesis\\BrazoRobotico\\src\\gui\\kinematics_worker.py", "source_location": "L102", "weight": 1.0}, {"source": "gui_kinematics_worker_kinematicsworker_ci", "target": "gui_kinematics_worker_kinematicsworker_jacobiano_analitico", "relation": "calls", "context": "call", "confidence": "EXTRACTED", "source_file": "C:\\Users\\jvele\\Documents\\_Tesis\\BrazoRobotico\\src\\gui\\kinematics_worker.py", "source_location": "L107", "weight": 1.0}, {"source": "gui_kinematics_worker_kinematicsworker_set_target", "target": "gui_kinematics_worker_kinematicsworker_update_sensor_data", "relation": "calls", "context": "call", "confidence": "EXTRACTED", "source_file": "C:\\Users\\jvele\\Documents\\_Tesis\\BrazoRobotico\\src\\gui\\kinematics_worker.py", "source_location": "L129", "weight": 1.0}, {"source": "gui_kinematics_worker_kinematicsworker_update_sensor_data", "target": "gui_kinematics_worker_kinematicsworker_cd", "relation": "calls", "context": "call", "confidence": "EXTRACTED", "source_file": "C:\\Users\\jvele\\Documents\\_Tesis\\BrazoRobotico\\src\\gui\\kinematics_worker.py", "source_location": "L166", "weight": 1.0}, {"source": "gui_kinematics_worker_kinematicsworker_update_sensor_data", "target": "gui_kinematics_worker_kinematicsworker_jacobiano_analitico", "relation": "calls", "context": "call", "confidence": "EXTRACTED", "source_file": "C:\\Users\\jvele\\Documents\\_Tesis\\BrazoRobotico\\src\\gui\\kinematics_worker.py", "source_location": "L177", "weight": 1.0}, {"source": "gui_kinematics_worker_rationale_1", "target": "c_users_jvele_documents_tesis_brazorobotico_src_gui_kinematics_worker_py", "relation": "rationale_for", "confidence": "EXTRACTED", "source_file": "C:\\Users\\jvele\\Documents\\_Tesis\\BrazoRobotico\\src\\gui\\kinematics_worker.py", "source_location": "L1", "weight": 1.0}, {"source": "gui_kinematics_worker_rationale_116", "target": "gui_kinematics_worker_kinematicsworker_set_target", "relation": "rationale_for", "confidence": "EXTRACTED", "source_file": "C:\\Users\\jvele\\Documents\\_Tesis\\BrazoRobotico\\src\\gui\\kinematics_worker.py", "source_location": "L116", "weight": 1.0}, {"source": "gui_kinematics_worker_rationale_132", "target": "gui_kinematics_worker_kinematicsworker_update_sensor_data", "relation": "rationale_for", "confidence": "EXTRACTED", "source_file": "C:\\Users\\jvele\\Documents\\_Tesis\\BrazoRobotico\\src\\gui\\kinematics_worker.py", "source_location": "L132", "weight": 1.0}], "raw_calls": [{"caller_nid": "gui_kinematics_worker_kinematicsworker_init", "callee": "super", "is_member_call": false, "source_file": "C:\\Users\\jvele\\Documents\\_Tesis\\BrazoRobotico\\src\\gui\\kinematics_worker.py", "source_location": "L22"}, {"caller_nid": "gui_kinematics_worker_kinematicsworker_init", "callee": "list", "is_member_call": false, "source_file": "C:\\Users\\jvele\\Documents\\_Tesis\\BrazoRobotico\\src\\gui\\kinematics_worker.py", "source_location": "L32"}, {"caller_nid": "gui_kinematics_worker_kinematicsworker_init", "callee": "get_instance", "is_member_call": true, "source_file": "C:\\Users\\jvele\\Documents\\_Tesis\\BrazoRobotico\\src\\gui\\kinematics_worker.py", "source_location": "L36"}, {"caller_nid": "gui_kinematics_worker_kinematicsworker_init", "callee": "connect", "is_member_call": true, "source_file": "C:\\Users\\jvele\\Documents\\_Tesis\\BrazoRobotico\\src\\gui\\kinematics_worker.py", "source_location": "L38"}, {"caller_nid": "gui_kinematics_worker_kinematicsworker_h_dh", "callee": "reshape", "is_member_call": true, "source_file": "C:\\Users\\jvele\\Documents\\_Tesis\\BrazoRobotico\\src\\gui\\kinematics_worker.py", "source_location": "L42"}, {"caller_nid": "gui_kinematics_worker_kinematicsworker_h_dh", "callee": "array", "is_member_call": true, "source_file": "C:\\Users\\jvele\\Documents\\_Tesis\\BrazoRobotico\\src\\gui\\kinematics_worker.py", "source_location": "L43"}, {"caller_nid": "gui_kinematics_worker_kinematicsworker_hrx", "callee": "cos", "is_member_call": true, "source_file": "C:\\Users\\jvele\\Documents\\_Tesis\\BrazoRobotico\\src\\gui\\kinematics_worker.py", "source_location": "L46"}, {"caller_nid": "gui_kinematics_worker_kinematicsworker_hrx", "callee": "sin", "is_member_call": true, "source_file": "C:\\Users\\jvele\\Documents\\_Tesis\\BrazoRobotico\\src\\gui\\kinematics_worker.py", "source_location": "L46"}, {"caller_nid": "gui_kinematics_worker_kinematicsworker_hrx", "callee": "array", "is_member_call": true, "source_file": "C:\\Users\\jvele\\Documents\\_Tesis\\BrazoRobotico\\src\\gui\\kinematics_worker.py", "source_location": "L47"}, {"caller_nid": "gui_kinematics_worker_kinematicsworker_hrz", "callee": "cos", "is_member_call": true, "source_file": "C:\\Users\\jvele\\Documents\\_Tesis\\BrazoRobotico\\src\\gui\\kinematics_worker.py", "source_location": "L50"}, {"caller_nid": "gui_kinematics_worker_kinematicsworker_hrz", "callee": "sin", "is_member_call": true, "source_file": "C:\\Users\\jvele\\Documents\\_Tesis\\BrazoRobotico\\src\\gui\\kinematics_worker.py", "source_location": "L50"}, {"caller_nid": "gui_kinematics_worker_kinematicsworker_hrz", "callee": "array", "is_member_call": true, "source_file": "C:\\Users\\jvele\\Documents\\_Tesis\\BrazoRobotico\\src\\gui\\kinematics_worker.py", "source_location": "L51"}, {"caller_nid": "gui_kinematics_worker_kinematicsworker_htx", "callee": "array", "is_member_call": true, "source_file": "C:\\Users\\jvele\\Documents\\_Tesis\\BrazoRobotico\\src\\gui\\kinematics_worker.py", "source_location": "L54"}, {"caller_nid": "gui_kinematics_worker_kinematicsworker_htz", "callee": "array", "is_member_call": true, "source_file": "C:\\Users\\jvele\\Documents\\_Tesis\\BrazoRobotico\\src\\gui\\kinematics_worker.py", "source_location": "L57"}, {"caller_nid": "gui_kinematics_worker_kinematicsworker_t_matrices", "callee": "identity", "is_member_call": true, "source_file": "C:\\Users\\jvele\\Documents\\_Tesis\\BrazoRobotico\\src\\gui\\kinematics_worker.py", "source_location": "L70"}, {"caller_nid": "gui_kinematics_worker_kinematicsworker_jacobiano_analitico", "callee": "reshape", "is_member_call": true, "source_file": "C:\\Users\\jvele\\Documents\\_Tesis\\BrazoRobotico\\src\\gui\\kinematics_worker.py", "source_location": "L80"}, {"caller_nid": "gui_kinematics_worker_kinematicsworker_jacobiano_analitico", "callee": "zeros", "is_member_call": true, "source_file": "C:\\Users\\jvele\\Documents\\_Tesis\\BrazoRobotico\\src\\gui\\kinematics_worker.py", "source_location": "L81"}, {"caller_nid": "gui_kinematics_worker_kinematicsworker_jacobiano_analitico", "callee": "range", "is_member_call": false, "source_file": "C:\\Users\\jvele\\Documents\\_Tesis\\BrazoRobotico\\src\\gui\\kinematics_worker.py", "source_location": "L82"}, {"caller_nid": "gui_kinematics_worker_kinematicsworker_jacobiano_analitico", "callee": "reshape", "is_member_call": true, "source_file": "C:\\Users\\jvele\\Documents\\_Tesis\\BrazoRobotico\\src\\gui\\kinematics_worker.py", "source_location": "L84"}, {"caller_nid": "gui_kinematics_worker_kinematicsworker_jacobiano_analitico", "callee": "reshape", "is_member_call": true, "source_file": "C:\\Users\\jvele\\Documents\\_Tesis\\BrazoRobotico\\src\\gui\\kinematics_worker.py", "source_location": "L85"}, {"caller_nid": "gui_kinematics_worker_kinematicsworker_jacobiano_analitico", "callee": "cross", "is_member_call": true, "source_file": "C:\\Users\\jvele\\Documents\\_Tesis\\BrazoRobotico\\src\\gui\\kinematics_worker.py", "source_location": "L87"}, {"caller_nid": "gui_kinematics_worker_kinematicsworker_jacobiano_analitico", "callee": "flatten", "is_member_call": true, "source_file": "C:\\Users\\jvele\\Documents\\_Tesis\\BrazoRobotico\\src\\gui\\kinematics_worker.py", "source_location": "L87"}, {"caller_nid": "gui_kinematics_worker_kinematicsworker_jacobiano_analitico", "callee": "flatten", "is_member_call": true, "source_file": "C:\\Users\\jvele\\Documents\\_Tesis\\BrazoRobotico\\src\\gui\\kinematics_worker.py", "source_location": "L87"}, {"caller_nid": "gui_kinematics_worker_kinematicsworker_ci", "callee": "reshape", "is_member_call": true, "source_file": "C:\\Users\\jvele\\Documents\\_Tesis\\BrazoRobotico\\src\\gui\\kinematics_worker.py", "source_location": "L97"}, {"caller_nid": "gui_kinematics_worker_kinematicsworker_ci", "callee": "deg2rad", "is_member_call": true, "source_file": "C:\\Users\\jvele\\Documents\\_Tesis\\BrazoRobotico\\src\\gui\\kinematics_worker.py", "source_location": "L97"}, {"caller_nid": "gui_kinematics_worker_kinematicsworker_ci", "callee": "array", "is_member_call": true, "source_file": "C:\\Users\\jvele\\Documents\\_Tesis\\BrazoRobotico\\src\\gui\\kinematics_worker.py", "source_location": "L97"}, {"caller_nid": "gui_kinematics_worker_kinematicsworker_ci", "callee": "array", "is_member_call": true, "source_file": "C:\\Users\\jvele\\Documents\\_Tesis\\BrazoRobotico\\src\\gui\\kinematics_worker.py", "source_location": "L100"}, {"caller_nid": "gui_kinematics_worker_kinematicsworker_ci", "callee": "range", "is_member_call": false, "source_file": "C:\\Users\\jvele\\Documents\\_Tesis\\BrazoRobotico\\src\\gui\\kinematics_worker.py", "source_location": "L101"}, {"caller_nid": "gui_kinematics_worker_kinematicsworker_ci", "callee": "norm", "is_member_call": true, "source_file": "C:\\Users\\jvele\\Documents\\_Tesis\\BrazoRobotico\\src\\gui\\kinematics_worker.py", "source_location": "L105"}, {"caller_nid": "gui_kinematics_worker_kinematicsworker_ci", "callee": "flatten", "is_member_call": true, "source_file": "C:\\Users\\jvele\\Documents\\_Tesis\\BrazoRobotico\\src\\gui\\kinematics_worker.py", "source_location": "L107"}, {"caller_nid": "gui_kinematics_worker_kinematicsworker_ci", "callee": "pinv", "is_member_call": true, "source_file": "C:\\Users\\jvele\\Documents\\_Tesis\\BrazoRobotico\\src\\gui\\kinematics_worker.py", "source_location": "L108"}, {"caller_nid": "gui_kinematics_worker_kinematicsworker_ci", "callee": "clip", "is_member_call": true, "source_file": "C:\\Users\\jvele\\Documents\\_Tesis\\BrazoRobotico\\src\\gui\\kinematics_worker.py", "source_location": "L109"}, {"caller_nid": "gui_kinematics_worker_kinematicsworker_set_target", "callee": "array", "is_member_call": true, "source_file": "C:\\Users\\jvele\\Documents\\_Tesis\\BrazoRobotico\\src\\gui\\kinematics_worker.py", "source_location": "L123"}, {"caller_nid": "gui_kinematics_worker_kinematicsworker_set_target", "callee": "time", "is_member_call": true, "source_file": "C:\\Users\\jvele\\Documents\\_Tesis\\BrazoRobotico\\src\\gui\\kinematics_worker.py", "source_location": "L126"}, {"caller_nid": "gui_kinematics_worker_kinematicsworker_set_target", "callee": "list", "is_member_call": false, "source_file": "C:\\Users\\jvele\\Documents\\_Tesis\\BrazoRobotico\\src\\gui\\kinematics_worker.py", "source_location": "L127"}, {"caller_nid": "gui_kinematics_worker_kinematicsworker_update_sensor_data", "callee": "list", "is_member_call": false, "source_file": "C:\\Users\\jvele\\Documents\\_Tesis\\BrazoRobotico\\src\\gui\\kinematics_worker.py", "source_location": "L140"}, {"caller_nid": "gui_kinematics_worker_kinematicsworker_update_sensor_data", "callee": "time", "is_member_call": true, "source_file": "C:\\Users\\jvele\\Documents\\_Tesis\\BrazoRobotico\\src\\gui\\kinematics_worker.py", "source_location": "L146"}, {"caller_nid": "gui_kinematics_worker_kinematicsworker_update_sensor_data", "callee": "sum", "is_member_call": false, "source_file": "C:\\Users\\jvele\\Documents\\_Tesis\\BrazoRobotico\\src\\gui\\kinematics_worker.py", "source_location": "L147"}, {"caller_nid": "gui_kinematics_worker_kinematicsworker_update_sensor_data", "callee": "abs", "is_member_call": false, "source_file": "C:\\Users\\jvele\\Documents\\_Tesis\\BrazoRobotico\\src\\gui\\kinematics_worker.py", "source_location": "L147"}, {"caller_nid": "gui_kinematics_worker_kinematicsworker_update_sensor_data", "callee": "print", "is_member_call": false, "source_file": "C:\\Users\\jvele\\Documents\\_Tesis\\BrazoRobotico\\src\\gui\\kinematics_worker.py", "source_location": "L150"}, {"caller_nid": "gui_kinematics_worker_kinematicsworker_update_sensor_data", "callee": "list", "is_member_call": false, "source_file": "C:\\Users\\jvele\\Documents\\_Tesis\\BrazoRobotico\\src\\gui\\kinematics_worker.py", "source_location": "L154"}, {"caller_nid": "gui_kinematics_worker_kinematicsworker_update_sensor_data", "callee": "reshape", "is_member_call": true, "source_file": "C:\\Users\\jvele\\Documents\\_Tesis\\BrazoRobotico\\src\\gui\\kinematics_worker.py", "source_location": "L158"}, {"caller_nid": "gui_kinematics_worker_kinematicsworker_update_sensor_data", "callee": "array", "is_member_call": true, "source_file": "C:\\Users\\jvele\\Documents\\_Tesis\\BrazoRobotico\\src\\gui\\kinematics_worker.py", "source_location": "L158"}, {"caller_nid": "gui_kinematics_worker_kinematicsworker_update_sensor_data", "callee": "deg2rad", "is_member_call": true, "source_file": "C:\\Users\\jvele\\Documents\\_Tesis\\BrazoRobotico\\src\\gui\\kinematics_worker.py", "source_location": "L159"}, {"caller_nid": "gui_kinematics_worker_kinematicsworker_update_sensor_data", "callee": "deg2rad", "is_member_call": true, "source_file": "C:\\Users\\jvele\\Documents\\_Tesis\\BrazoRobotico\\src\\gui\\kinematics_worker.py", "source_location": "L160"}, {"caller_nid": "gui_kinematics_worker_kinematicsworker_update_sensor_data", "callee": "deg2rad", "is_member_call": true, "source_file": "C:\\Users\\jvele\\Documents\\_Tesis\\BrazoRobotico\\src\\gui\\kinematics_worker.py", "source_location": "L161"}, {"caller_nid": "gui_kinematics_worker_kinematicsworker_update_sensor_data", "callee": "deg2rad", "is_member_call": true, "source_file": "C:\\Users\\jvele\\Documents\\_Tesis\\BrazoRobotico\\src\\gui\\kinematics_worker.py", "source_location": "L162"}, {"caller_nid": "gui_kinematics_worker_kinematicsworker_update_sensor_data", "callee": "norm", "is_member_call": true, "source_file": "C:\\Users\\jvele\\Documents\\_Tesis\\BrazoRobotico\\src\\gui\\kinematics_worker.py", "source_location": "L168"}, {"caller_nid": "gui_kinematics_worker_kinematicsworker_update_sensor_data", "callee": "flatten", "is_member_call": true, "source_file": "C:\\Users\\jvele\\Documents\\_Tesis\\BrazoRobotico\\src\\gui\\kinematics_worker.py", "source_location": "L177"}, {"caller_nid": "gui_kinematics_worker_kinematicsworker_update_sensor_data", "callee": "inv", "is_member_call": true, "source_file": "C:\\Users\\jvele\\Documents\\_Tesis\\BrazoRobotico\\src\\gui\\kinematics_worker.py", "source_location": "L178"}, {"caller_nid": "gui_kinematics_worker_kinematicsworker_update_sensor_data", "callee": "eye", "is_member_call": true, "source_file": "C:\\Users\\jvele\\Documents\\_Tesis\\BrazoRobotico\\src\\gui\\kinematics_worker.py", "source_location": "L178"}, {"caller_nid": "gui_kinematics_worker_kinematicsworker_update_sensor_data", "callee": "clip", "is_member_call": true, "source_file": "C:\\Users\\jvele\\Documents\\_Tesis\\BrazoRobotico\\src\\gui\\kinematics_worker.py", "source_location": "L180"}, {"caller_nid": "gui_kinematics_worker_kinematicsworker_update_sensor_data", "callee": "deg2rad", "is_member_call": true, "source_file": "C:\\Users\\jvele\\Documents\\_Tesis\\BrazoRobotico\\src\\gui\\kinematics_worker.py", "source_location": "L180"}, {"caller_nid": "gui_kinematics_worker_kinematicsworker_update_sensor_data", "callee": "deg2rad", "is_member_call": true, "source_file": "C:\\Users\\jvele\\Documents\\_Tesis\\BrazoRobotico\\src\\gui\\kinematics_worker.py", "source_location": "L180"}, {"caller_nid": "gui_kinematics_worker_kinematicsworker_update_sensor_data", "callee": "clip", "is_member_call": true, "source_file": "C:\\Users\\jvele\\Documents\\_Tesis\\BrazoRobotico\\src\\gui\\kinematics_worker.py", "source_location": "L181"}, {"caller_nid": "gui_kinematics_worker_kinematicsworker_update_sensor_data", "callee": "deg2rad", "is_member_call": true, "source_file": "C:\\Users\\jvele\\Documents\\_Tesis\\BrazoRobotico\\src\\gui\\kinematics_worker.py", "source_location": "L181"}, {"caller_nid": "gui_kinematics_worker_kinematicsworker_update_sensor_data", "callee": "deg2rad", "is_member_call": true, "source_file": "C:\\Users\\jvele\\Documents\\_Tesis\\BrazoRobotico\\src\\gui\\kinematics_worker.py", "source_location": "L181"}, {"caller_nid": "gui_kinematics_worker_kinematicsworker_update_sensor_data", "callee": "rad2deg", "is_member_call": true, "source_file": "C:\\Users\\jvele\\Documents\\_Tesis\\BrazoRobotico\\src\\gui\\kinematics_worker.py", "source_location": "L184"}, {"caller_nid": "gui_kinematics_worker_kinematicsworker_update_sensor_data", "callee": "flatten", "is_member_call": true, "source_file": "C:\\Users\\jvele\\Documents\\_Tesis\\BrazoRobotico\\src\\gui\\kinematics_worker.py", "source_location": "L184"}, {"caller_nid": "gui_kinematics_worker_kinematicsworker_update_sensor_data", "callee": "list", "is_member_call": false, "source_file": "C:\\Users\\jvele\\Documents\\_Tesis\\BrazoRobotico\\src\\gui\\kinematics_worker.py", "source_location": "L185"}, {"caller_nid": "gui_kinematics_worker_kinematicsworker_update_sensor_data", "callee": "max", "is_member_call": false, "source_file": "C:\\Users\\jvele\\Documents\\_Tesis\\BrazoRobotico\\src\\gui\\kinematics_worker.py", "source_location": "L192"}, {"caller_nid": "gui_kinematics_worker_kinematicsworker_update_sensor_data", "callee": "min", "is_member_call": false, "source_file": "C:\\Users\\jvele\\Documents\\_Tesis\\BrazoRobotico\\src\\gui\\kinematics_worker.py", "source_location": "L192"}, {"caller_nid": "gui_kinematics_worker_kinematicsworker_update_sensor_data", "callee": "emit", "is_member_call": true, "source_file": "C:\\Users\\jvele\\Documents\\_Tesis\\BrazoRobotico\\src\\gui\\kinematics_worker.py", "source_location": "L195"}]}